<?xml version="1.0" encoding="utf-8" ?>
<Symbols>
<Symbol code="102108100" title="102108100" />
<Symbol code="102108101" title="102108101" />
<Symbol code="102108102" title="102108102" />
<Symbol code="102108103" title="102108103" />
<Symbol code="102108104" title="102108104" />
<Symbol code="102108105" title="102108105" />
<Symbol code="102108106" title="102108106" />
<Symbol code="102108107" title="102108107" />
<Symbol code="102108108" title="102108108" />
<Symbol code="102108109" title="102108109" />
<Symbol code="102108110" title="102108110" />
<Symbol code="102108111" title="102108111" />
<Symbol code="102108112" title="102108112" />
<Symbol code="102108113" title="102108113" />
<Symbol code="102108114" title="102108114" />
<Symbol code="102108115" title="102108115" />
<Symbol code="102108116" title="102108116" />
<Symbol code="102108117" title="102108117" />
<Symbol code="102108118" title="102108118" />
<Symbol code="102108119" title="102108119" />
<Symbol code="102108120" title="102108120" />
<Symbol code="102108121" title="102108121" />
<Symbol code="102108122" title="102108122" />
<Symbol code="102108123" title="102108123" />
<Symbol code="102108124" title="102108124" />
<Symbol code="102108125" title="102108125" />
<Symbol code="102108126" title="102108126" />
<Symbol code="102108127" title="102108127" />
<Symbol code="102108128" title="102108128" />
<Symbol code="102108129" title="102108129" />
<Symbol code="102108130" title="102108130" />
<Symbol code="102108131" title="102108131" />
<Symbol code="102108132" title="102108132" />
<Symbol code="102108133" title="102108133" />
<Symbol code="102108134" title="102108134" />
<Symbol code="102108135" title="102108135" />
<Symbol code="102108136" title="102108136" />
<Symbol code="102108137" title="102108137" />
<Symbol code="102108138" title="102108138" />
<Symbol code="102108139" title="102108139" />
<Symbol code="102108140" title="102108140" />
<Symbol code="102108141" title="102108141" />
<Symbol code="102108142" title="102108142" />
<Symbol code="102108143" title="102108143" />
<Symbol code="102108144" title="102108144" />
<Symbol code="102108145" title="102108145" />
<Symbol code="102108146" title="102108146" />
<Symbol code="102108147" title="102108147" />
<Symbol code="102108148" title="102108148" />
<Symbol code="102108149" title="102108149" />
</Symbols>
