<?xml version="1.0" encoding="utf-8" ?>
<Symbols>
<Symbol code="103101100" title="103101100" />
<Symbol code="103101101" title="103101101" />
<Symbol code="103101102" title="103101102" />
<Symbol code="103101103" title="103101103" />
<Symbol code="103101104" title="103101104" />
<Symbol code="103101105" title="103101105" />
<Symbol code="103101106" title="103101106" />
<Symbol code="103101107" title="103101107" />
<Symbol code="103101108" title="103101108" />
<Symbol code="103101109" title="103101109" />
<Symbol code="103101110" title="103101110" />
<Symbol code="103101111" title="103101111" />
<Symbol code="103101112" title="103101112" />
<Symbol code="103101113" title="103101113" />
<Symbol code="103101114" title="103101114" />
<Symbol code="103101115" title="103101115" />
<Symbol code="103101116" title="103101116" />
<Symbol code="103101117" title="103101117" />
<Symbol code="103101118" title="103101118" />
<Symbol code="103101119" title="103101119" />
<Symbol code="103101120" title="103101120" />
<Symbol code="103101121" title="103101121" />
<Symbol code="103101122" title="103101122" />
<Symbol code="103101123" title="103101123" />
<Symbol code="103101124" title="103101124" />
<Symbol code="103101125" title="103101125" />
<Symbol code="103101126" title="103101126" />
<Symbol code="103101127" title="103101127" />
<Symbol code="103101128" title="103101128" />
<Symbol code="103101129" title="103101129" />
<Symbol code="103101130" title="103101130" />
<Symbol code="103101131" title="103101131" />
<Symbol code="103101132" title="103101132" />
<Symbol code="103101133" title="103101133" />
<Symbol code="103101134" title="103101134" />
<Symbol code="103101135" title="103101135" />
<Symbol code="103101136" title="103101136" />
<Symbol code="103101137" title="103101137" />
<Symbol code="103101138" title="103101138" />
<Symbol code="103101139" title="103101139" />
<Symbol code="103101140" title="103101140" />
<Symbol code="103101141" title="103101141" />
<Symbol code="103101142" title="103101142" />
<Symbol code="103101143" title="103101143" />
<Symbol code="103101144" title="103101144" />
<Symbol code="103101145" title="103101145" />
<Symbol code="103101146" title="103101146" />
<Symbol code="103101147" title="103101147" />
<Symbol code="103101148" title="103101148" />
<Symbol code="103101149" title="103101149" />
<Symbol code="103101150" title="103101150" />
<Symbol code="103101151" title="103101151" />
<Symbol code="103101152" title="103101152" />
<Symbol code="103101153" title="103101153" />
<Symbol code="103101154" title="103101154" />
<Symbol code="103101155" title="103101155" />
<Symbol code="103101156" title="103101156" />
<Symbol code="103101157" title="103101157" />
<Symbol code="103101158" title="103101158" />
</Symbols>
