<?xml version="1.0" encoding="utf-8" ?>
<Symbols>
<Symbol code="110135100" title="110135100" />
<Symbol code="110135101" title="110135101" />
<Symbol code="110135102" title="110135102" />
<Symbol code="110135103" title="110135103" />
<Symbol code="110135104" title="110135104" />
<Symbol code="110135105" title="110135105" />
<Symbol code="110135106" title="110135106" />
<Symbol code="110135107" title="110135107" />
<Symbol code="110135108" title="110135108" />
<Symbol code="110135109" title="110135109" />
<Symbol code="110135110" title="110135110" />
<Symbol code="110135111" title="110135111" />
<Symbol code="110135112" title="110135112" />
<Symbol code="110135113" title="110135113" />
<Symbol code="110135114" title="110135114" />
<Symbol code="110135115" title="110135115" />
<Symbol code="110135116" title="110135116" />
<Symbol code="110135117" title="110135117" />
<Symbol code="110135118" title="110135118" />
<Symbol code="110135119" title="110135119" />
<Symbol code="110135120" title="110135120" />
<Symbol code="110135121" title="110135121" />
<Symbol code="110135122" title="110135122" />
<Symbol code="110135123" title="110135123" />
<Symbol code="110135124" title="110135124" />
<Symbol code="110135125" title="110135125" />
<Symbol code="110135126" title="110135126" />
<Symbol code="110135127" title="110135127" />
<Symbol code="110135128" title="110135128" />
<Symbol code="110135129" title="110135129" />
<Symbol code="110135130" title="110135130" />
<Symbol code="110135131" title="110135131" />
<Symbol code="110135132" title="110135132" />
<Symbol code="110135133" title="110135133" />
<Symbol code="110135134" title="110135134" />
<Symbol code="110135135" title="110135135" />
<Symbol code="110135136" title="110135136" />
<Symbol code="110135137" title="110135137" />
<Symbol code="110135138" title="110135138" />
<Symbol code="110135139" title="110135139" />
<Symbol code="110135140" title="110135140" />
<Symbol code="110135141" title="110135141" />
<Symbol code="110135142" title="110135142" />
<Symbol code="110135143" title="110135143" />
<Symbol code="110135144" title="110135144" />
<Symbol code="110135145" title="110135145" />
<Symbol code="110135146" title="110135146" />
<Symbol code="110135147" title="110135147" />
<Symbol code="110135148" title="110135148" />
<Symbol code="110135149" title="110135149" />
<Symbol code="110135150" title="110135150" />
<Symbol code="110135151" title="110135151" />
<Symbol code="110135152" title="110135152" />
<Symbol code="110135153" title="110135153" />
<Symbol code="110135154" title="110135154" />
<Symbol code="110135155" title="110135155" />
<Symbol code="110135156" title="110135156" />
<Symbol code="110135157" title="110135157" />
<Symbol code="110135158" title="110135158" />
<Symbol code="110135159" title="110135159" />
<Symbol code="110135160" title="110135160" />
<Symbol code="110135161" title="110135161" />
<Symbol code="110135162" title="110135162" />
<Symbol code="110135163" title="110135163" />
<Symbol code="110135164" title="110135164" />
<Symbol code="110135165" title="110135165" />
<Symbol code="110135166" title="110135166" />
<Symbol code="110135167" title="110135167" />
<Symbol code="110135168" title="110135168" />
<Symbol code="110135169" title="110135169" />
<Symbol code="110135170" title="110135170" />
<Symbol code="110135171" title="110135171" />
<Symbol code="110135172" title="110135172" />
<Symbol code="110135173" title="110135173" />
<Symbol code="110135174" title="110135174" />
<Symbol code="110135175" title="110135175" />
<Symbol code="110135176" title="110135176" />
<Symbol code="110135177" title="110135177" />
<Symbol code="110135178" title="110135178" />
<Symbol code="110135179" title="110135179" />
<Symbol code="110135180" title="110135180" />
<Symbol code="110135181" title="110135181" />
<Symbol code="110135182" title="110135182" />
<Symbol code="110135183" title="110135183" />
<Symbol code="110135184" title="110135184" />
<Symbol code="110135185" title="110135185" />
<Symbol code="110135186" title="110135186" />
<Symbol code="110135187" title="110135187" />
<Symbol code="110135188" title="110135188" />
<Symbol code="110135189" title="110135189" />
<Symbol code="110135190" title="110135190" />
<Symbol code="110135191" title="110135191" />
<Symbol code="110135192" title="110135192" />
<Symbol code="110135193" title="110135193" />
<Symbol code="110135194" title="110135194" />
<Symbol code="110135195" title="110135195" />
<Symbol code="110135196" title="110135196" />
</Symbols>
